{
  "mini-css-extract-plugin node_modules/@zeit/next-css/node_modules/css-loader/index.js??ref--5-1!pages/index.css": [
    {
      "modules": {
        "byIdentifier": {},
        "usedIds": {}
      },
      "chunks": {
        "byName": {
          "mini-css-extract-plugin": 0
        },
        "bySource": {},
        "usedIds": [
          0
        ]
      }
    }
  ],
  "mini-css-extract-plugin node_modules/@zeit/next-css/node_modules/css-loader/index.js??ref--5-1!node_modules/gestalt/dist/gestalt.css": [
    {
      "modules": {
        "byIdentifier": {},
        "usedIds": {}
      },
      "chunks": {
        "byName": {
          "mini-css-extract-plugin": 0
        },
        "bySource": {},
        "usedIds": [
          0
        ]
      }
    }
  ],
  "modules": {
    "byIdentifier": {
      "css node_modules/@zeit/next-css/node_modules/css-loader/index.js??ref--5-1!node_modules/gestalt/dist/gestalt.css 0": 0,
      "css node_modules/@zeit/next-css/node_modules/css-loader/index.js??ref--5-1!pages/index.css 0": 1
    },
    "usedIds": {
      "0": 0,
      "1": 1
    }
  },
  "chunks": {
    "byName": {
      "static/runtime/webpack.js": 0,
      "commons": 1,
      "static/9EZxkYfsaeaMk-bmSalU-/pages/_app.js": 2,
      "static/9EZxkYfsaeaMk-bmSalU-/pages/_error.js": 3,
      "static/9EZxkYfsaeaMk-bmSalU-/pages/game.js": 4,
      "static/9EZxkYfsaeaMk-bmSalU-/pages/index.js": 5,
      "static/9EZxkYfsaeaMk-bmSalU-/pages/login.js": 6,
      "static/runtime/main.js": 7,
      "static/runtime/polyfills.js": 8
    },
    "bySource": {},
    "usedIds": [
      0,
      1,
      2,
      3,
      4,
      5,
      6,
      7,
      8
    ]
  }
}